{"cameraMode":{"drawMode":0,"name":"Shaded","section":"Shading Mode"},"sceneLighting":false,"audioPlay":false,"sceneViewState":{"m_AlwaysRefresh":false,"showFog":true,"showSkybox":false,"showFlares":true,"showImageEffects":true,"showParticleSystems":true,"showVisualEffectGraphs":true,"m_FxEnabled":true},"in2DMode":false,"pivot":{"x":-3.0999999046325685,"y":1.13149094581604,"z":22.814289093017579},"rotation":{"x":0.3583623170852661,"y":-0.15577411651611329,"z":0.0607776902616024,"w":0.9184867143630981},"size":1.982822060585022,"orthographic":true}